{
  "expectation_suite_name": "demographics_suite",
  "meta": {
    "great_expectations_version": "0.18.0"
  },
  "expectations": [
    {
      "expectation_type": "expect_table_columns_to_match_ordered_list",
      "kwargs": {
        "column_list": ["zipcode", "population", "median_income", "median_age"]
      },
      "meta": {}
    },
    {
      "expectation_type": "expect_column_values_to_not_be_null",
      "kwargs": {
        "column": "zipcode"
      },
      "meta": {}
    },
    {
      "expectation_type": "expect_column_values_to_be_unique",
      "kwargs": {
        "column": "zipcode"
      },
      "meta": {}
    },
    {
      "expectation_type": "expect_column_values_to_be_between",
      "kwargs": {
        "column": "population",
        "min_value": 1000,
        "max_value": 100000
      },
      "meta": {}
    },
    {
      "expectation_type": "expect_column_values_to_be_between",
      "kwargs": {
        "column": "median_income",
        "min_value": 20000,
        "max_value": 200000
      },
      "meta": {}
    }
  ]
}
